MofanGitJiaocheng2017510/README.md
MofanGitJiaocheng2017510/__init__.py
MofanGitJiaocheng2017510/__main__.py
MofanGitJiaocheng2017510/file.epub
MofanGitJiaocheng2017510/index.html
MofanGitJiaocheng2017510/css/__init__.py
MofanGitJiaocheng2017510/css/annotations.css
MofanGitJiaocheng2017510/css/main.css
MofanGitJiaocheng2017510/css/normalize.css
MofanGitJiaocheng2017510/css/popup.css
MofanGitJiaocheng2017510/font/__init__.py
MofanGitJiaocheng2017510/font/fontello.eot
MofanGitJiaocheng2017510/font/fontello.svg
MofanGitJiaocheng2017510/font/fontello.ttf
MofanGitJiaocheng2017510/font/fontello.woff
MofanGitJiaocheng2017510/img/__init__.py
MofanGitJiaocheng2017510/img/annotator-glyph-sprite.png
MofanGitJiaocheng2017510/img/annotator-icon-sprite.png
MofanGitJiaocheng2017510/img/apple-touch-icon.png
MofanGitJiaocheng2017510/img/cancelfullscreen.png
MofanGitJiaocheng2017510/img/close.png
MofanGitJiaocheng2017510/img/fullscreen.png
MofanGitJiaocheng2017510/img/loader.gif
MofanGitJiaocheng2017510/img/menu-icon.png
MofanGitJiaocheng2017510/img/save.png
MofanGitJiaocheng2017510/img/saved.png
MofanGitJiaocheng2017510/img/settings-s.png
MofanGitJiaocheng2017510/img/settings.png
MofanGitJiaocheng2017510/img/star.png
MofanGitJiaocheng2017510/js/__init__.py
MofanGitJiaocheng2017510/js/epub.js
MofanGitJiaocheng2017510/js/epub.min.js
MofanGitJiaocheng2017510/js/epub.min.map
MofanGitJiaocheng2017510/js/hooks.min.js
MofanGitJiaocheng2017510/js/hooks.min.map
MofanGitJiaocheng2017510/js/reader.js
MofanGitJiaocheng2017510/js/reader.js.map
MofanGitJiaocheng2017510/js/reader.min.js
MofanGitJiaocheng2017510/js/reader.min.map
MofanGitJiaocheng2017510/js/hooks/__init__.py
MofanGitJiaocheng2017510/js/hooks/extensions/__init__.py
MofanGitJiaocheng2017510/js/hooks/extensions/highlight.js
MofanGitJiaocheng2017510/js/libs/__init__.py
MofanGitJiaocheng2017510/js/libs/jquery.min.js
MofanGitJiaocheng2017510/js/libs/localforage.min.js
MofanGitJiaocheng2017510/js/libs/screenfull.js
mofan_git_jiaocheng_2017_5_10-2024.3.2.0.dist-info/METADATA
mofan_git_jiaocheng_2017_5_10-2024.3.2.0.dist-info/WHEEL
mofan_git_jiaocheng_2017_5_10-2024.3.2.0.dist-info/entry_points.txt
mofan_git_jiaocheng_2017_5_10-2024.3.2.0.dist-info/top_level.txt
mofan_git_jiaocheng_2017_5_10-2024.3.2.0.dist-info/RECORD
